package_api/Untitled-1.py
package_api/__init__.py
package_api/oops.py
MEGABANK_API-0.3.dist-info/METADATA
MEGABANK_API-0.3.dist-info/WHEEL
MEGABANK_API-0.3.dist-info/top_level.txt
MEGABANK_API-0.3.dist-info/RECORD
