Metadata-Version: 2.1
Name: MEGABANK-API
Version: 0.3
Summary: API package that provides us the method to fetch the data from the API, along with the method to convert that into proper dataframe
Author: Dinesh
Author-email: dineshsugumar289@gmail.com
License: MIT
Requires-Dist: pandas
Requires-Dist: requests
